setup.py
rps_arief/__init__.py
rps_arief/rps_arief.py
rps_arief.egg-info/PKG-INFO
rps_arief.egg-info/SOURCES.txt
rps_arief.egg-info/dependency_links.txt
rps_arief.egg-info/not-zip-safe
rps_arief.egg-info/top_level.txt