Metadata-Version: 1.0
Name: rps-arief
Version: 0.2
Summary: Rock Paper Scissors game
Home-page: UNKNOWN
Author: Arief Ramadhan
Author-email: arief25ramadhan@gmail.com
License: UNKNOWN
Platform: UNKNOWN
